{
  "brand": "Crescent",
  "type": "Mountainbike",
  "model": "Lodur",
  "year": "1997",
  "description": "Aggressiv tävlingscykel med komponenter på hög nivå till ett pris på medelnivå. Exklusiv Cromo-ram med reducerade rör och en utvändig out-spiral trådförstärkning, som ger extra stabilitet, vridstyvhet och en egen karaktär. V-brake och 24 växlar på LX-nivå. Silent Clutch baknav, som rullar utan tick och svarar direkt på pedaltryck. Nytt förstärkt vevparti, styre och sadel. Separerade broms- och växelreglage. Rå följeslagare med personlighet.",
  "images": [
    {
      "description": "Cykelpraktikan 1997",
      "filename": "crescent-lodur-1997-01.jpg"
    },
    {
      "description": "Cykelpraktikan 1997",
      "filename": "crescent-lodur-1997-02.jpg"
    }
  ]
}
